ulid/__init__.py
ulid/__main__.py
ulid/base32.py
ulid/constants.py
ulid/py.typed
python_ulid-2.5.0.dist-info/METADATA
python_ulid-2.5.0.dist-info/WHEEL
python_ulid-2.5.0.dist-info/entry_points.txt
python_ulid-2.5.0.dist-info/licenses/LICENSE
python_ulid-2.5.0.dist-info/RECORD
